moonalloy/__init__.py
moonalloy/linalg/__init__.py
moonalloy/linalg/array.py
moonalloy/linalg/ffi.py
moonalloy/linalg/matrix.py
moonalloy/linalg/test_array_internal.py
moonalloy/linalg/test/__init__.py
moonalloy/linalg/test/test_array.py
python_moonalloy-0.0.1.dist-info/LICENSE
python_moonalloy-0.0.1.dist-info/METADATA
python_moonalloy-0.0.1.dist-info/WHEEL
python_moonalloy-0.0.1.dist-info/top_level.txt
python_moonalloy-0.0.1.dist-info/RECORD
