Metadata-Version: 2.1
Name: python-moonalloy
Version: 0.0.1
Summary: Python bindings for MoonAlloy
Home-page: https://git.hacktheoxidation.xyz/python-moonalloy.git/
Author: HackTheOxidation
Author-email: tomas.hagenau@protonmail.dh
Classifier: Programming Language :: Python :: 3
Classifier: License :: OSI Approved :: MIT License
Classifier: Operating System :: OS Independent
Requires-Python: >=3.6
License-File: LICENSE
